README.md
setup.cfg
setup.py
catapult_docs_cli/__init__.py
catapult_docs_cli/cli.py
catapult_docs_cli/utils.py
catapult_docs_cli/commands/__init__.py
catapult_docs_cli/commands/base.py
catapult_docs_cli/commands/cli_usage.py
catapult_docs_cli/commands/properties.py
catapult_docs_cli/commands/status_errors.py
catapultdocscli.egg-info/PKG-INFO
catapultdocscli.egg-info/SOURCES.txt
catapultdocscli.egg-info/dependency_links.txt
catapultdocscli.egg-info/entry_points.txt
catapultdocscli.egg-info/not-zip-safe
catapultdocscli.egg-info/requires.txt
catapultdocscli.egg-info/top_level.txt
tests/test_commands/__init__.py
tests/test_commands/test_base.py
tests/test_commands/test_properties.py
tests/test_commands/test_status_errors.py