Metadata-Version: 1.1
Name: catapultdocscli
Version: 0.2.4
Summary: Exports some documentation from catapult code into reStructuredText tables.
Home-page: https://github.com/nemtech/catapult-docs-cli
Author: David Garcia (@dgarcia360)
Author-email: david@nem.foundation
License: MIT
Platform: any
Classifier: Development Status :: 4 - Beta
Classifier: Environment :: Console
Classifier: Intended Audience :: Developers
Classifier: License :: OSI Approved :: BSD License
Classifier: Operating System :: POSIX
Classifier: Operating System :: MacOS
Classifier: Operating System :: Unix
Classifier: Operating System :: Microsoft :: Windows
Classifier: Programming Language :: Python
Classifier: Programming Language :: Python :: 2
Classifier: Programming Language :: Python :: 3
Classifier: Topic :: Software Development :: Libraries :: Python Modules
